pe_analyzer/__init__.py
pe_analyzer/pe_analyzer.py
pe_analyzer/tests/test_pe_analyzer.py
pe_analyzer/tests/testBin.exe
pe_analyzer/tests/testBinSrc.cpp
pe_analyzer-0.1.2.dist-info/LICENSE
pe_analyzer-0.1.2.dist-info/METADATA
pe_analyzer-0.1.2.dist-info/WHEEL
pe_analyzer-0.1.2.dist-info/RECORD
