Metadata-Version: 2.1
Name: pe-analyzer
Version: 0.1.2
Summary: A Python module to analyze Portable Executable (PE) files on Windows systems. It parses and extracts various details about the file header, optional header, sections, imports, and exports. The module provides an easy-to-use class, PEAnalyzer, which returns analysis data in JSON format and supports pretty-printing of the information when used with the print() function.
License: MIT
Author: DJ Stomp
Author-email: 85457381+DJStompZone@users.noreply.github.com
Requires-Python: >=3.10,<4.0
Classifier: License :: OSI Approved :: MIT License
Classifier: Operating System :: OS Independent
Classifier: Programming Language :: Python :: 3
Classifier: Programming Language :: Python :: 3.10
Classifier: Programming Language :: Python :: 3.11
Classifier: Programming Language :: Python :: 3
Requires-Dist: pefile (>=2023.2.7,<2024.0.0)
